odoo/addons/geoengine_partner/README.rst
odoo/addons/geoengine_partner/__init__.py
odoo/addons/geoengine_partner/__manifest__.py
odoo/addons/geoengine_partner/i18n/geoengine_partner.pot
odoo/addons/geoengine_partner/models/__init__.py
odoo/addons/geoengine_partner/models/partner.py
odoo/addons/geoengine_partner/readme/CONTRIBUTORS.rst
odoo/addons/geoengine_partner/readme/CREDITS.rst
odoo/addons/geoengine_partner/readme/DESCRIPTION.rst
odoo/addons/geoengine_partner/readme/INSTALL.rst
odoo/addons/geoengine_partner/readme/USAGE.rst
odoo/addons/geoengine_partner/static/description/icon.png
odoo/addons/geoengine_partner/static/description/index.html
odoo/addons/geoengine_partner/views/partner.xml
odoo13_addon_geoengine_partner-13.0.1.0.1.dev5.dist-info/METADATA
odoo13_addon_geoengine_partner-13.0.1.0.1.dev5.dist-info/WHEEL
odoo13_addon_geoengine_partner-13.0.1.0.1.dev5.dist-info/top_level.txt
odoo13_addon_geoengine_partner-13.0.1.0.1.dev5.dist-info/RECORD
